<?xml version="1.0" encoding="UTF-8"?>
<rows>
  <head>
    
    <column id="No" width="50" type="ro" align="center" sort="na"></column>
    <column id="InstrumentCode" width="*" type="ro" align="left" sort="na">headerInstrumentCode</column>
    <column id="Qty" width="180" type="ron2" align="right" numberformat="#,##0" sort="na">headerQty</column>
    <column id="CostUsD" width="180" type="ron2" align="right" numberformat="US$#,##0.00" sort="na">headerCost</column>
    <column id="TotalUsD" width="220" type="ron2" align="right" numberformat="US$#,##0.00" sort="na">headerTotal</column>
    <column id="SlipNo" width="0" type="ro" hidden="true"></column>
    <column id="StockInDate" width="0" type="ro" hidden="true"></column>
    
    <settings>
      <colwidth>px</colwidth>
    </settings>
  </head>
</rows>